{"v":"5.7.4","fr":30,"ip":0,"op":90,"w":1080,"h":1080,"nm":"littie_pop_heart_001","ddd":0,"assets":[{"id":"comp_0","layers":[{"ddd":0,"ind":1,"ty":4,"nm":"Glitter","sr":1,"ks":{"o":{"a":0,"k":100,"ix":11},"r":{"a":0,"k":0,"ix":10},"p":{"a":0,"k":[540,540,0],"ix":2,"l":2},"a":{"a":0,"k":[454.5,473.5,0],"ix":1,"l":2},"s":{"a":1,"k":[{"i":{"x":[0,0,0.667],"y":[1,1,1]},"o":{"x":[0,0,0.333],"y":[0,0,0]},"t":57,"s":[0,0,100]},{"i":{"x":[0.778,0.778,0.667],"y":[1,1,1]},"o":{"x":[0.275,0.275,0.333],"y":[0,0,0]},"t":59,"s":[100,100,100]},{"i":{"x":[1,1,0.667],"y":[1,1,1]},"o":{"x":[1,1,0.333],"y":[0,0,0]},"t":62,"s":[100,100,100]},{"i":{"x":[0.833,0.833,0.833],"y":[1,1,1]},"o":{"x":[0.167,0.167,0.167],"y":[0,0,0]},"t":64,"s":[0,0,100]},{"i":{"x":[0,0,0.667],"y":[1,1,1]},"o":{"x":[0,0,0.333],"y":[0,0,0]},"t":71,"s":[0,0,100]},{"i":{"x":[0.778,0.778,0.667],"y":[1,1,1]},"o":{"x":[0.275,0.275,0.333],"y":[0,0,0]},"t":73,"s":[100,100,100]},{"i":{"x":[1,1,0.667],"y":[1,1,1]},"o":{"x":[1,1,0.333],"y":[0,0,0]},"t":76,"s":[100,100,100]},{"t":78,"s":[0,0,100]}],"ix":6,"l":2}},"ao":0,"shapes":[{"ty":"gr","it":[{"ind":0,"ty":"sh","ix":1,"ks":{"a":0,"k":{"i":[[0,0],[94.73,-105.254],[0,0],[94.729,105.255],[0,0],[-94.729,105.254],[0,0],[-94.729,-105.255]],"o":[[0,0],[-94.729,105.255],[0,0],[-94.729,-105.254],[0,0],[94.729,-105.255],[0,0],[94.73,105.254]],"v":[[454,0],[129.079,146.254],[0,473.078],[-129.079,146.254],[-454,0],[-129.079,-146.254],[0,-473.078],[129.079,-146.254]],"c":true},"ix":2},"nm":"パス 1","mn":"ADBE Vector Shape - Group","hd":false},{"ty":"fl","c":{"a":0,"k":[1,0.870588235294,0,1],"ix":4},"o":{"a":0,"k":100,"ix":5},"r":1,"bm":0,"nm":"塗り 1","mn":"ADBE Vector Graphic - Fill","hd":false},{"ty":"tr","p":{"a":0,"k":[454.25,473.328],"ix":2},"a":{"a":0,"k":[0,0],"ix":1},"s":{"a":0,"k":[100,100],"ix":3},"r":{"a":0,"k":0,"ix":6},"o":{"a":0,"k":100,"ix":7},"sk":{"a":0,"k":0,"ix":4},"sa":{"a":0,"k":0,"ix":5},"nm":"トランスフォーム"}],"nm":"グループ 1","np":2,"cix":2,"bm":0,"ix":1,"mn":"ADBE Vector Group","hd":false}],"ip":0,"op":180,"st":0,"bm":0}]},{"id":"comp_1","layers":[{"ddd":0,"ind":1,"ty":4,"nm":"Glitter","sr":1,"ks":{"o":{"a":0,"k":100,"ix":11},"r":{"a":0,"k":0,"ix":10},"p":{"a":0,"k":[540,540,0],"ix":2,"l":2},"a":{"a":0,"k":[454.5,473.5,0],"ix":1,"l":2},"s":{"a":1,"k":[{"i":{"x":[0,0,0.667],"y":[1,1,1]},"o":{"x":[0.093,0.093,0.333],"y":[0,0,0]},"t":50,"s":[0,0,100]},{"i":{"x":[0.833,0.833,0.833],"y":[1,1,1]},"o":{"x":[0.333,0.333,0.333],"y":[0,0,0]},"t":52,"s":[100,100,100]},{"i":{"x":[1,1,0.833],"y":[1,1,1]},"o":{"x":[1,1,0.167],"y":[0,0,0]},"t":55,"s":[100,100,100]},{"i":{"x":[0.833,0.833,0.833],"y":[1,1,1]},"o":{"x":[0.167,0.167,0.167],"y":[0,0,0]},"t":57,"s":[0,0,100]},{"i":{"x":[0,0,0.667],"y":[1,1,1]},"o":{"x":[0.093,0.093,0.333],"y":[0,0,0]},"t":64,"s":[0,0,100]},{"i":{"x":[0.833,0.833,0.833],"y":[1,1,1]},"o":{"x":[0.333,0.333,0.333],"y":[0,0,0]},"t":66,"s":[100,100,100]},{"i":{"x":[1,1,0.833],"y":[1,1,1]},"o":{"x":[1,1,0.167],"y":[0,0,0]},"t":69,"s":[100,100,100]},{"i":{"x":[0.833,0.833,0.833],"y":[1,1,1]},"o":{"x":[0.167,0.167,0.167],"y":[0,0,0]},"t":71,"s":[0,0,100]},{"i":{"x":[0,0,0.667],"y":[1,1,1]},"o":{"x":[0.093,0.093,0.333],"y":[0,0,0]},"t":78,"s":[0,0,100]},{"i":{"x":[0.833,0.833,0.833],"y":[1,1,1]},"o":{"x":[0.333,0.333,0.333],"y":[0,0,0]},"t":80,"s":[100,100,100]},{"i":{"x":[1,1,0.833],"y":[1,1,1]},"o":{"x":[1,1,0.167],"y":[0,0,0]},"t":83,"s":[100,100,100]},{"t":85,"s":[0,0,100]}],"ix":6,"l":2}},"ao":0,"shapes":[{"ty":"gr","it":[{"ind":0,"ty":"sh","ix":1,"ks":{"a":0,"k":{"i":[[0,0],[94.73,-105.254],[0,0],[94.729,105.255],[0,0],[-94.729,105.254],[0,0],[-94.729,-105.255]],"o":[[0,0],[-94.729,105.255],[0,0],[-94.729,-105.254],[0,0],[94.729,-105.255],[0,0],[94.73,105.254]],"v":[[454,0],[129.079,146.254],[0,473.078],[-129.079,146.254],[-454,0],[-129.079,-146.254],[0,-473.078],[129.079,-146.254]],"c":true},"ix":2},"nm":"パス 1","mn":"ADBE Vector Shape - Group","hd":false},{"ty":"fl","c":{"a":0,"k":[1,0.870588295133,0,1],"ix":4},"o":{"a":0,"k":100,"ix":5},"r":1,"bm":0,"nm":"塗り 1","mn":"ADBE Vector Graphic - Fill","hd":false},{"ty":"tr","p":{"a":0,"k":[454.25,473.328],"ix":2},"a":{"a":0,"k":[0,0],"ix":1},"s":{"a":0,"k":[100,100],"ix":3},"r":{"a":0,"k":0,"ix":6},"o":{"a":0,"k":100,"ix":7},"sk":{"a":0,"k":0,"ix":4},"sa":{"a":0,"k":0,"ix":5},"nm":"トランスフォーム"}],"nm":"グループ 1","np":2,"cix":2,"bm":0,"ix":1,"mn":"ADBE Vector Group","hd":false}],"ip":0,"op":180,"st":0,"bm":0}]}],"layers":[{"ddd":0,"ind":1,"ty":0,"nm":"Glitter_002","refId":"comp_0","sr":1,"ks":{"o":{"a":0,"k":100,"ix":11},"r":{"a":0,"k":0,"ix":10},"p":{"a":0,"k":[148,446,0],"ix":2,"l":2},"a":{"a":0,"k":[540,540,0],"ix":1,"l":2},"s":{"a":0,"k":[20,20,100],"ix":6,"l":2}},"ao":0,"w":1080,"h":1080,"ip":0,"op":180,"st":0,"bm":0},{"ddd":0,"ind":2,"ty":0,"nm":"Glitter_002","refId":"comp_0","sr":1,"ks":{"o":{"a":0,"k":100,"ix":11},"r":{"a":0,"k":0,"ix":10},"p":{"a":0,"k":[898,666,0],"ix":2,"l":2},"a":{"a":0,"k":[540,540,0],"ix":1,"l":2},"s":{"a":0,"k":[15,15,100],"ix":6,"l":2}},"ao":0,"w":1080,"h":1080,"ip":0,"op":180,"st":0,"bm":0},{"ddd":0,"ind":3,"ty":0,"nm":"Glitter_002","refId":"comp_0","sr":1,"ks":{"o":{"a":0,"k":100,"ix":11},"r":{"a":0,"k":0,"ix":10},"p":{"a":0,"k":[256,196,0],"ix":2,"l":2},"a":{"a":0,"k":[540,540,0],"ix":1,"l":2},"s":{"a":0,"k":[15,15,100],"ix":6,"l":2}},"ao":0,"w":1080,"h":1080,"ip":0,"op":180,"st":0,"bm":0},{"ddd":0,"ind":4,"ty":0,"nm":"Glitter_002","refId":"comp_0","sr":1,"ks":{"o":{"a":0,"k":100,"ix":11},"r":{"a":0,"k":0,"ix":10},"p":{"a":0,"k":[790,908,0],"ix":2,"l":2},"a":{"a":0,"k":[540,540,0],"ix":1,"l":2},"s":{"a":0,"k":[20,20,100],"ix":6,"l":2}},"ao":0,"w":1080,"h":1080,"ip":0,"op":180,"st":0,"bm":0},{"ddd":0,"ind":5,"ty":0,"nm":"Glitter_001","refId":"comp_1","sr":1,"ks":{"o":{"a":0,"k":100,"ix":11},"r":{"a":0,"k":0,"ix":10},"p":{"a":0,"k":[132,948,0],"ix":2,"l":2},"a":{"a":0,"k":[540,540,0],"ix":1,"l":2},"s":{"a":0,"k":[15,15,100],"ix":6,"l":2}},"ao":0,"w":1080,"h":1080,"ip":0,"op":180,"st":0,"bm":0},{"ddd":0,"ind":6,"ty":0,"nm":"Glitter_001","refId":"comp_1","sr":1,"ks":{"o":{"a":0,"k":100,"ix":11},"r":{"a":0,"k":0,"ix":10},"p":{"a":0,"k":[224,816,0],"ix":2,"l":2},"a":{"a":0,"k":[540,540,0],"ix":1,"l":2},"s":{"a":0,"k":[20,20,100],"ix":6,"l":2}},"ao":0,"w":1080,"h":1080,"ip":0,"op":180,"st":0,"bm":0},{"ddd":0,"ind":7,"ty":0,"nm":"Glitter_001","refId":"comp_1","sr":1,"ks":{"o":{"a":0,"k":100,"ix":11},"r":{"a":0,"k":0,"ix":10},"p":{"a":0,"k":[850,280,0],"ix":2,"l":2},"a":{"a":0,"k":[540,540,0],"ix":1,"l":2},"s":{"a":0,"k":[30,30,100],"ix":6,"l":2}},"ao":0,"w":1080,"h":1080,"ip":0,"op":180,"st":0,"bm":0},{"ddd":0,"ind":8,"ty":4,"nm":"Heart","sr":1,"ks":{"o":{"a":0,"k":100,"ix":11},"r":{"a":0,"k":0,"ix":10},"p":{"a":0,"k":[540,540,0],"ix":2,"l":2},"a":{"a":0,"k":[579.5,485,0],"ix":1,"l":2},"s":{"a":1,"k":[{"i":{"x":[0.667,0.667,0.667],"y":[1,1,1]},"o":{"x":[0.333,0.333,0.333],"y":[0,0,0]},"t":10,"s":[100,100,100]},{"i":{"x":[0.667,0.667,0.667],"y":[1,1,1]},"o":{"x":[0.333,0.333,0.333],"y":[0,0,0]},"t":21,"s":[90,90,100]},{"i":{"x":[0.667,0.667,0.667],"y":[1,1,1]},"o":{"x":[0.333,0.333,0.333],"y":[0,0,0]},"t":24,"s":[100,100,100]},{"i":{"x":[0.667,0.667,0.667],"y":[1,1,1]},"o":{"x":[0.333,0.333,0.333],"y":[0,0,0]},"t":27,"s":[120,120,100]},{"t":30,"s":[100,100,100]}],"ix":6,"l":2}},"ao":0,"shapes":[{"ty":"gr","it":[{"ind":0,"ty":"sh","ix":1,"ks":{"a":0,"k":{"i":[[0,0],[-119.86,175.704],[235,-292.384],[-185,-271.192]],"o":[[0,0],[185,-271.192],[-235,-292.384],[119.861,175.704]],"v":[[0,461],[394,146.192],[0,-168.616],[-394,146.192]],"c":true},"ix":2},"nm":"パス 1","mn":"ADBE Vector Shape - Group","hd":false},{"ty":"fl","c":{"a":0,"k":[0.933333333333,0.281830043419,0.404466097963,1],"ix":4},"o":{"a":0,"k":100,"ix":5},"r":1,"bm":0,"nm":"塗り 1","mn":"ADBE Vector Graphic - Fill","hd":false},{"ty":"tr","p":{"a":0,"k":[579.25,461.25],"ix":2},"a":{"a":0,"k":[0,0],"ix":1},"s":{"a":0,"k":[90,90],"ix":3},"r":{"a":0,"k":0,"ix":6},"o":{"a":0,"k":100,"ix":7},"sk":{"a":0,"k":0,"ix":4},"sa":{"a":0,"k":0,"ix":5},"nm":"トランスフォーム"}],"nm":"グループ 2","np":4,"cix":2,"bm":0,"ix":1,"mn":"ADBE Vector Group","hd":false}],"ip":0,"op":90,"st":0,"bm":0}],"markers":[]}